{
  "users": [
    {
      "name": "Joel Wehner",
      "dob": "1975-9-17",
      "email": "Joel.Wehner@gmail.com",
      "username": "Joel_Wehner99",
      "password": "wzyNmlLa64RcHxq",
      "phone": "394.235.0780 x548",
      "streetaddress": "4837 Stoltenberg Village",
      "citystatezip": "Port Turnerport, NM 52170",
      "latitude": "-68.5887",
      "longitude": "-72.0632",
      "avatar": "https://s3.amazonaws.com/uifaces/faces/twitter/wesleytrankin/128.jpg"
    },
    {
      "name": "Kiarra Walsh",
      "dob": "1973-8-8",
      "email": "Kiarra38@gmail.com",
      "username": "Kiarra66",
      "password": "MqFg7dfiYIT85qy",
      "phone": "235-836-7246",
      "streetaddress": "7731 Cloyd Light",
      "citystatezip": "Cruickshankburgh, KS 63038",
      "latitude": "39.3445",
      "longitude": "63.4460",
      "avatar": "https://s3.amazonaws.com/uifaces/faces/twitter/hjartstrorn/128.jpg"
    },
    {
      "name": "Lucius Dickinson",
      "dob": "1989-5-7",
      "email": "Lucius.Dickinson63@yahoo.com",
      "username": "Lucius_Dickinson80",
      "password": "E3sDLuvNlWu8Qsz",
      "phone": "571.419.3870 x529",
      "streetaddress": "17239 Therese Point",
      "citystatezip": "Zboncakberg, SC 50802",
      "latitude": "3.2847",
      "longitude": "-33.2913",
      "avatar": "https://s3.amazonaws.com/uifaces/faces/twitter/carlyson/128.jpg"
    }
  ]
}